paquo/.paquo.defaults.toml
paquo/__init__.py
paquo/__main__.py
paquo/_cli.py
paquo/_config.py
paquo/_logging.py
paquo/_repr.py
paquo/_utils.py
paquo/_version.py
paquo/classes.py
paquo/colors.py
paquo/hierarchy.py
paquo/images.py
paquo/java.py
paquo/jpype_backend.py
paquo/pathobjects.py
paquo/projects.py
paquo/py.typed
paquo-0.9.0.dist-info/LICENSE
paquo-0.9.0.dist-info/METADATA
paquo-0.9.0.dist-info/WHEEL
paquo-0.9.0.dist-info/entry_points.txt
paquo-0.9.0.dist-info/top_level.txt
paquo-0.9.0.dist-info/RECORD
